comet_for_mlflow/__init__.py
comet_for_mlflow/cli.py
comet_for_mlflow/comet_for_mlflow.py
comet_for_mlflow/compat.py
comet_for_mlflow/file_writer.py
comet_for_mlflow/utils.py
comet_for_mlflow-0.1.9.dist-info/licenses/AUTHORS.rst
comet_for_mlflow-0.1.9.dist-info/licenses/LICENSE
comet_for_mlflow-0.1.9.dist-info/METADATA
comet_for_mlflow-0.1.9.dist-info/WHEEL
comet_for_mlflow-0.1.9.dist-info/entry_points.txt
comet_for_mlflow-0.1.9.dist-info/top_level.txt
comet_for_mlflow-0.1.9.dist-info/RECORD
