Metadata-Version: 2.4
Name: comet_for_mlflow
Version: 0.1.9
Summary: Extend MLFlow with Comet.ml
Home-page: https://github.com/comet-ml/comet-for-mlflow
Author: Boris Feld
Author-email: boris@comet.ml
License: GNU General Public License v3
Keywords: comet_for_mlflow
Classifier: Development Status :: 2 - Pre-Alpha
Classifier: Intended Audience :: Developers
Classifier: License :: OSI Approved :: GNU General Public License v3 (GPLv3)
Classifier: Natural Language :: English
Classifier: Programming Language :: Python :: 2
Classifier: Programming Language :: Python :: 2.7
Classifier: Programming Language :: Python :: 3
Classifier: Programming Language :: Python :: 3.5
Classifier: Programming Language :: Python :: 3.6
Classifier: Programming Language :: Python :: 3.7
Requires-Python: >=2.7, !=3.0.*, !=3.1.*, !=3.2.*, !=3.3.*
License-File: LICENSE
License-File: AUTHORS.rst
Requires-Dist: mlflow
Requires-Dist: comet_ml>=3.39.0
Requires-Dist: tabulate
Requires-Dist: tqdm
Requires-Dist: typing
Dynamic: author
Dynamic: author-email
Dynamic: classifier
Dynamic: description
Dynamic: description-content-type
Dynamic: home-page
Dynamic: keywords
Dynamic: license
Dynamic: license-file
Dynamic: requires-dist
Dynamic: requires-python
Dynamic: summary
